nvdlfw_inspect/__init__.py
nvdlfw_inspect/api.py
nvdlfw_inspect/base.py
nvdlfw_inspect/config_manager.py
nvdlfw_inspect/debug_manager.py
nvdlfw_inspect/logging.py
nvdlfw_inspect/registry.py
nvdlfw_inspect/utils.py
nvdlfw_inspect/debug_features/__init__.py
nvdlfw_inspect/debug_features/generic_feature_api.py
nvdlfw_inspect/debug_features/log_tensor_stats.py
nvdlfw_inspect-0.2.2.dist-info/licenses/LICENSE
nvdlfw_inspect-0.2.2.dist-info/METADATA
nvdlfw_inspect-0.2.2.dist-info/WHEEL
nvdlfw_inspect-0.2.2.dist-info/top_level.txt
nvdlfw_inspect-0.2.2.dist-info/RECORD
