Metadata-Version: 2.4
Name: nvdlfw_inspect
Version: 0.2.2
Summary: Facilitates debugging convergence issues and testing new algorithms/recipes for training LLMs using Nvidia libraries.
Home-page: https://github.com/NVIDIA/nvidia-dlfw-inspect
Author: NVIDIA Corporation
License: Apache2
Classifier: Development Status :: 4 - Beta
Classifier: Programming Language :: Python :: 3
Classifier: Programming Language :: Python :: 3.6
Classifier: Operating System :: OS Independent
Requires-Python: >=3.8
License-File: LICENSE
Requires-Dist: pyyaml>=6.0.0
Requires-Dist: torch>=2.1.0
Provides-Extra: dev
Requires-Dist: pre-commit==4.1.0; extra == "dev"
Requires-Dist: pytest==8.1.1; extra == "dev"
Requires-Dist: ruff==0.9.3; extra == "dev"
Dynamic: author
Dynamic: classifier
Dynamic: description
Dynamic: description-content-type
Dynamic: home-page
Dynamic: license
Dynamic: license-file
Dynamic: provides-extra
Dynamic: requires-dist
Dynamic: requires-python
Dynamic: summary
